{"grid": {"width": 13, "height": 21, "cells": [{"x": 0, "y": 0, "type": "DEF", "letter": null, "defs": [{"direction": "RIGHT_DOWN", "clue_text": ""}, {"direction": "DOWN", "clue_text": ""}]}, {"x": 1, "y": 0, "type": "LETTER", "letter": "O", "defs": []}, {"x": 2, "y": 0, "type": "DEF", "letter": null, "defs": [{"direction": "RIGHT_DOWN", "clue_text": ""}, {"direction": "DOWN", "clue_text": ""}]}, {"x": 3, "y": 0, "type": "LETTER", "letter": "A", "defs": []}, {"x": 4, "y": 0, "type": "DEF", "letter": null, "defs": [{"direction": "RIGHT_DOWN", "clue_text": ""}, {"direction": "DOWN", "clue_text": ""}]}, {"x": 5, "y": 0, "type": "LETTER", "letter": "F", "defs": []}, {"x": 6, "y": 0, "type": "DEF", "letter": null, "defs": [{"direction": "RIGHT_DOWN", "clue_text": ""}, {"direction": "DOWN", "clue_text": ""}]}, {"x": 7, "y": 0, "type": "LETTER", "letter": "A", "defs": []}, {"x": 8, "y": 0, "type": "DEF", "letter": null, "defs": [{"direction": "RIGHT_DOWN", "clue_text": ""}, {"direction": "DOWN", "clue_text": ""}]}, {"x": 9, "y": 0, "type": null, "letter": null, "defs": []}, {"x": 10, "y": 0, "type": "DEF", "letter": null, "defs": [{"direction": "RIGHT_DOWN", "clue_text": ""}, {"direction": "DOWN", "clue_text": ""}]}, {"x": 11, "y": 0, "type": null, "letter": null, "defs": []}, {"x": 12, "y": 0, "type": "DEF", "letter": null, "defs": [{"direction": "RIGHT_DOWN", "clue_text": ""}, {"direction": "DOWN", "clue_text": ""}]}, {"x": 0, "y": 1, "type": "LETTER", "letter": "T", "defs": []}, {"x": 1, "y": 1, "type": "LETTER", "letter": "U", "defs": []}, {"x": 2, "y": 1, "type": "DEF", "letter": null, "defs": [{"direction": "RIGHT", "clue_text": ""}, {"direction": "RIGHT_DOWN", "clue_text": ""}]}, {"x": 3, "y": 1, "type": "LETTER", "letter": "B", "defs": []}, {"x": 4, "y": 1, "type": null, "letter": null, "defs": []}, {"x": 5, "y": 1, "type": "LETTER", "letter": "O", "defs": []}, {"x": 6, "y": 1, "type": "LETTER", "letter": "S", "defs": []}, {"x": 7, "y": 1, "type": "LETTER", "letter": "L", "defs": []}, {"x": 8, "y": 1, "type": "LETTER", "letter": "O", "defs": []}, {"x": 9, "y": 1, "type": null, "letter": null, "defs": []}, {"x": 10, "y": 1, "type": "LETTER", "letter": "C", "defs": []}, {"x": 11, "y": 1, "type": null, "letter": null, "defs": []}, {"x": 12, "y": 1, "type": "LETTER", "letter": "L", "defs": []}, {"x": 0, "y": 2, "type": "DEF", "letter": null, "defs": [{"direction": "RIGHT", "clue_text": ""}, {"direction": "RIGHT_DOWN", "clue_text": ""}]}, {"x": 1, "y": 2, "type": "LETTER", "letter": "E", "defs": []}, {"x": 2, "y": 2, "type": "LETTER", "letter": "X", "defs": []}, {"x": 3, "y": 2, "type": "LETTER", "letter": "C", "defs": []}, {"x": 4, "y": 2, "type": "LETTER", "letter": "L", "defs": []}, {"x": 5, "y": 2, "type": "LETTER", "letter": "U", "defs": []}, {"x": 6, "y": 2, "type": "LETTER", "letter": "T", "defs": []}, {"x": 7, "y": 2, "type": "DEF", "letter": null, "defs": [{"direction": "RIGHT", "clue_text": ""}, {"direction": "RIGHT_DOWN", "clue_text": ""}]}, {"x": 8, "y": 2, "type": "LETTER", "letter": "U", "defs": []}, {"x": 9, "y": 2, "type": null, "letter": null, "defs": []}, {"x": 10, "y": 2, "type": "LETTER", "letter": "O", "defs": []}, {"x": 11, "y": 2, "type": null, "letter": null, "defs": []}, {"x": 12, "y": 2, "type": "LETTER", "letter": "A", "defs": []}, {"x": 0, "y": 3, "type": "LETTER", "letter": "O", "defs": []}, {"x": 1, "y": 3, "type": "LETTER", "letter": "S", "defs": []}, {"x": 2, "y": 3, "type": "DEF", "letter": null, "defs": [{"direction": "DOWN", "clue_text": ""}, {"direction": "RIGHT_DOWN", "clue_text": ""}]}, {"x": 3, "y": 3, "type": "DEF", "letter": null, "defs": [{"direction": "DOWN", "clue_text": ""}, {"direction": "RIGHT_DOWN", "clue_text": ""}]}, {"x": 4, "y": 3, "type": null, "letter": null, "defs": []}, {"x": 5, "y": 3, "type": "DEF", "letter": null, "defs": [{"direction": "RIGHT", "clue_text": ""}, {"direction": "DOWN", "clue_text": ""}, {"direction": "RIGHT_DOWN", "clue_text": ""}]}, {"x": 6, "y": 3, "type": "LETTER", "letter": "O", "defs": []}, {"x": 7, "y": 3, "type": null, "letter": null, "defs": []}, {"x": 8, "y": 3, "type": "LETTER", "letter": "R", "defs": []}, {"x": 9, "y": 3, "type": null, "letter": null, "defs": []}, {"x": 10, "y": 3, "type": "LETTER", "letter": "N", "defs": []}, {"x": 11, "y": 3, "type": null, "letter": null, "defs": []}, {"x": 12, "y": 3, "type": "LETTER", "letter": "T", "defs": []}, {"x": 0, "y": 4, "type": "DEF", "letter": null, "defs": [{"direction": "RIGHT", "clue_text": ""}, {"direction": "RIGHT_DOWN", "clue_text": ""}]}, {"x": 1, "y": 4, "type": "LETTER", "letter": "T", "defs": []}, {"x": 2, "y": 4, "type": "LETTER", "letter": "R", "defs": []}, {"x": 3, "y": 4, "type": "LETTER", "letter": "I", "defs": []}, {"x": 4, "y": 4, "type": "LETTER", "letter": "M", "defs": []}, {"x": 5, "y": 4, "type": "LETTER", "letter": "E", "defs": []}, {"x": 6, "y": 4, "type": "LETTER", "letter": "R", "defs": []}, {"x": 7, "y": 4, "type": "DEF", "letter": null, "defs": [{"direction": "RIGHT", "clue_text": ""}, {"direction": "RIGHT_DOWN", "clue_text": ""}]}, {"x": 8, "y": 4, "type": "LETTER", "letter": "L", "defs": []}, {"x": 9, "y": 4, "type": null, "letter": null, "defs": []}, {"x": 10, "y": 4, "type": "LETTER", "letter": "F", "defs": []}, {"x": 11, "y": 4, "type": null, "letter": null, "defs": []}, {"x": 12, "y": 4, "type": "LETTER", "letter": "T", "defs": []}, {"x": 0, "y": 5, "type": null, "letter": null, "defs": []}, {"x": 1, "y": 5, "type": "DEF", "letter": null, "defs": [{"direction": "RIGHT", "clue_text": ""}, {"direction": "DOWN", "clue_text": ""}, {"direction": "RIGHT_DOWN", "clue_text": ""}]}, {"x": 2, "y": 5, "type": "LETTER", "letter": "I", "defs": []}, {"x": 3, "y": 5, "type": null, "letter": null, "defs": []}, {"x": 4, "y": 5, "type": null, "letter": null, "defs": []}, {"x": 5, "y": 5, "type": "LETTER", "letter": "R", "defs": []}, {"x": 6, "y": 5, "type": "LETTER", "letter": "E", "defs": []}, {"x": 7, "y": 5, "type": null, "letter": null, "defs": []}, {"x": 8, "y": 5, "type": "LETTER", "letter": "E", "defs": []}, {"x": 9, "y": 5, "type": null, "letter": null, "defs": []}, {"x": 10, "y": 5, "type": "LETTER", "letter": "O", "defs": []}, {"x": 11, "y": 5, "type": null, "letter": null, "defs": []}, {"x": 12, "y": 5, "type": "LETTER", "letter": "E", "defs": []}, {"x": 0, "y": 6, "type": "DEF", "letter": null, "defs": [{"direction": "RIGHT", "clue_text": ""}, {"direction": "RIGHT_DOWN", "clue_text": ""}]}, {"x": 1, "y": 6, "type": "LETTER", "letter": "P", "defs": []}, {"x": 2, "y": 6, "type": "LETTER", "letter": "O", "defs": []}, {"x": 3, "y": 6, "type": "LETTER", "letter": "C", "defs": []}, {"x": 4, "y": 6, "type": "LETTER", "letter": "H", "defs": []}, {"x": 5, "y": 6, "type": "LETTER", "letter": "E", "defs": []}, {"x": 6, "y": 6, "type": "LETTER", "letter": "S", "defs": []}, {"x": 7, "y": 6, "type": "DEF", "letter": null, "defs": [{"direction": "DOWN", "clue_text": ""}, {"direction": "RIGHT_DOWN", "clue_text": ""}]}, {"x": 8, "y": 6, "type": "DEF", "letter": null, "defs": [{"direction": "RIGHT", "clue_text": ""}, {"direction": "DOWN", "clue_text": ""}]}, {"x": 9, "y": 6, "type": "LETTER", "letter": "I", "defs": []}, {"x": 10, "y": 6, "type": "LETTER", "letter": "R", "defs": []}, {"x": 11, "y": 6, "type": "LETTER", "letter": "E", "defs": []}, {"x": 12, "y": 6, "type": "DEF", "letter": null, "defs": [{"direction": "DOWN", "clue_text": ""}]}, {"x": 0, "y": 7, "type": null, "letter": null, "defs": []}, {"x": 1, "y": 7, "type": null, "letter": null, "defs": []}, {"x": 2, "y": 7, "type": "DEF", "letter": null, "defs": [{"direction": "RIGHT", "clue_text": ""}, {"direction": "DOWN", "clue_text": ""}, {"direction": "RIGHT_DOWN", "clue_text": ""}]}, {"x": 3, "y": 7, "type": null, "letter": null, "defs": []}, {"x": 4, "y": 7, "type": null, "letter": null, "defs": []}, {"x": 5, "y": 7, "type": "DEF", "letter": null, "defs": [{"direction": "DOWN", "clue_text": ""}, {"direction": "RIGHT_DOWN", "clue_text": ""}]}, {"x": 6, "y": 7, "type": "DEF", "letter": null, "defs": [{"direction": "RIGHT", "clue_text": ""}, {"direction": "DOWN", "clue_text": ""}, {"direction": "RIGHT_DOWN", "clue_text": ""}]}, {"x": 7, "y": 7, "type": "LETTER", "letter": "S", "defs": []}, {"x": 8, "y": 7, "type": "LETTER", "letter": "A", "defs": []}, {"x": 9, "y": 7, "type": "DEF", "letter": null, "defs": [{"direction": "RIGHT", "clue_text": ""}, {"direction": "DOWN", "clue_text": ""}]}, {"x": 10, "y": 7, "type": "LETTER", "letter": "T", "defs": []}, {"x": 11, "y": 7, "type": null, "letter": null, "defs": []}, {"x": 12, "y": 7, "type": "LETTER", "letter": "L", "defs": []}, {"x": 0, "y": 8, "type": "DEF", "letter": null, "defs": [{"direction": "RIGHT", "clue_text": ""}, {"direction": "RIGHT_DOWN", "clue_text": ""}]}, {"x": 1, "y": 8, "type": "LETTER", "letter": "V", "defs": []}, {"x": 2, "y": 8, "type": "LETTER", "letter": "E", "defs": []}, {"x": 3, "y": 8, "type": "LETTER", "letter": "R", "defs": []}, {"x": 4, "y": 8, "type": "LETTER", "letter": "S", "defs": []}, {"x": 5, "y": 8, "type": "LETTER", "letter": "A", "defs": []}, {"x": 6, "y": 8, "type": "LETTER", "letter": "T", "defs": []}, {"x": 7, "y": 8, "type": "LETTER", "letter": "I", "defs": []}, {"x": 8, "y": 8, "type": "LETTER", "letter": "L", "defs": []}, {"x": 9, "y": 8, "type": "LETTER", "letter": "E", "defs": []}, {"x": 10, "y": 8, "type": "DEF", "letter": null, "defs": [{"direction": "RIGHT", "clue_text": ""}, {"direction": "DOWN", "clue_text": ""}, {"direction": "RIGHT_DOWN", "clue_text": ""}]}, {"x": 11, "y": 8, "type": "LETTER", "letter": "T", "defs": []}, {"x": 12, "y": 8, "type": "LETTER", "letter": "A", "defs": []}, {"x": 0, "y": 9, "type": "LETTER", "letter": "S", "defs": []}, {"x": 1, "y": 9, "type": "LETTER", "letter": "A", "defs": []}, {"x": 2, "y": 9, "type": "LETTER", "letter": "M", "defs": []}, {"x": 3, "y": 9, "type": "DEF", "letter": null, "defs": [{"direction": "RIGHT", "clue_text": ""}, {"direction": "DOWN", "clue_text": ""}, {"direction": "RIGHT_DOWN", "clue_text": ""}]}, {"x": 4, "y": 9, "type": null, "letter": null, "defs": []}, {"x": 5, "y": 9, "type": null, "letter": null, "defs": []}, {"x": 6, "y": 9, "type": "LETTER", "letter": "E", "defs": []}, {"x": 7, "y": 9, "type": "LETTER", "letter": "T", "defs": []}, {"x": 8, "y": 9, "type": null, "letter": null, "defs": []}, {"x": 9, "y": 9, "type": "LETTER", "letter": "U", "defs": []}, {"x": 10, "y": 9, "type": null, "letter": null, "defs": []}, {"x": 11, "y": 9, "type": null, "letter": null, "defs": []}, {"x": 12, "y": 9, "type": "LETTER", "letter": "V", "defs": []}, {"x": 0, "y": 10, "type": "DEF", "letter": null, "defs": [{"direction": "RIGHT", "clue_text": ""}, {"direction": "RIGHT_DOWN", "clue_text": ""}]}, {"x": 1, "y": 10, "type": "LETTER", "letter": "L", "defs": []}, {"x": 2, "y": 10, "type": "LETTER", "letter": "U", "defs": []}, {"x": 3, "y": 10, "type": "LETTER", "letter": "M", "defs": []}, {"x": 4, "y": 10, "type": "LETTER", "letter": "I", "defs": []}, {"x": 5, "y": 10, "type": "LETTER", "letter": "N", "defs": []}, {"x": 6, "y": 10, "type": "LETTER", "letter": "E", "defs": []}, {"x": 7, "y": 10, "type": "LETTER", "letter": "U", "defs": []}, {"x": 8, "y": 10, "type": "LETTER", "letter": "X", "defs": []}, {"x": 9, "y": 10, "type": "DEF", "letter": null, "defs": [{"direction": "RIGHT", "clue_text": ""}, {"direction": "DOWN", "clue_text": ""}, {"direction": "RIGHT_DOWN", "clue_text": ""}]}, {"x": 10, "y": 10, "type": "LETTER", "letter": "D", "defs": []}, {"x": 11, "y": 10, "type": "LETTER", "letter": "U", "defs": []}, {"x": 12, "y": 10, "type": "LETTER", "letter": "E", "defs": []}, {"x": 0, "y": 11, "type": null, "letter": null, "defs": []}, {"x": 1, "y": 11, "type": null, "letter": null, "defs": []}, {"x": 2, "y": 11, "type": "DEF", "letter": null, "defs": [{"direction": "RIGHT", "clue_text": ""}, {"direction": "RIGHT_DOWN", "clue_text": ""}]}, {"x": 3, "y": 11, "type": null, "letter": null, "defs": []}, {"x": 4, "y": 11, "type": null, "letter": null, "defs": []}, {"x": 5, "y": 11, "type": null, "letter": null, "defs": []}, {"x": 6, "y": 11, "type": "DEF", "letter": null, "defs": [{"direction": "RIGHT", "clue_text": ""}, {"direction": "DOWN", "clue_text": ""}, {"direction": "RIGHT_DOWN", "clue_text": ""}]}, {"x": 7, "y": 11, "type": "LETTER", "letter": "E", "defs": []}, {"x": 8, "y": 11, "type": null, "letter": null, "defs": []}, {"x": 9, "y": 11, "type": "LETTER", "letter": "I", "defs": []}, {"x": 10, "y": 11, "type": null, "letter": null, "defs": []}, {"x": 11, "y": 11, "type": null, "letter": null, "defs": []}, {"x": 12, "y": 11, "type": "DEF", "letter": null, "defs": [{"direction": "DOWN", "clue_text": ""}]}, {"x": 0, "y": 12, "type": "DEF", "letter": null, "defs": [{"direction": "RIGHT", "clue_text": ""}, {"direction": "RIGHT_DOWN", "clue_text": ""}]}, {"x": 1, "y": 12, "type": "LETTER", "letter": "L", "defs": []}, {"x": 2, "y": 12, "type": "LETTER", "letter": "U", "defs": []}, {"x": 3, "y": 12, "type": "LETTER", "letter": "G", "defs": []}, {"x": 4, "y": 12, "type": "LETTER", "letter": "U", "defs": []}, {"x": 5, "y": 12, "type": "LETTER", "letter": "B", "defs": []}, {"x": 6, "y": 12, "type": "LETTER", "letter": "R", "defs": []}, {"x": 7, "y": 12, "type": "LETTER", "letter": "E", "defs": []}, {"x": 8, "y": 12, "type": "DEF", "letter": null, "defs": [{"direction": "RIGHT", "clue_text": ""}, {"direction": "DOWN", "clue_text": ""}, {"direction": "RIGHT_DOWN", "clue_text": ""}]}, {"x": 9, "y": 12, "type": "LETTER", "letter": "L", "defs": []}, {"x": 10, "y": 12, "type": "LETTER", "letter": "I", "defs": []}, {"x": 11, "y": 12, "type": "LETTER", "letter": "M", "defs": []}, {"x": 12, "y": 12, "type": "LETTER", "letter": "A", "defs": []}, {"x": 0, "y": 13, "type": "LETTER", "letter": "N", "defs": []}, {"x": 1, "y": 13, "type": "LETTER", "letter": "E", "defs": []}, {"x": 2, "y": 13, "type": "DEF", "letter": null, "defs": [{"direction": "RIGHT", "clue_text": ""}, {"direction": "DOWN", "clue_text": ""}, {"direction": "RIGHT_DOWN", "clue_text": ""}]}, {"x": 3, "y": 13, "type": null, "letter": null, "defs": []}, {"x": 4, "y": 13, "type": null, "letter": null, "defs": []}, {"x": 5, "y": 13, "type": null, "letter": null, "defs": []}, {"x": 6, "y": 13, "type": "LETTER", "letter": "A", "defs": []}, {"x": 7, "y": 13, "type": "DEF", "letter": null, "defs": [{"direction": "RIGHT", "clue_text": ""}, {"direction": "DOWN", "clue_text": ""}, {"direction": "RIGHT_DOWN", "clue_text": ""}]}, {"x": 8, "y": 13, "type": "LETTER", "letter": "C", "defs": []}, {"x": 9, "y": 13, "type": "DEF", "letter": null, "defs": [{"direction": "RIGHT", "clue_text": ""}, {"direction": "DOWN", "clue_text": ""}, {"direction": "RIGHT_DOWN", "clue_text": ""}]}, {"x": 10, "y": 13, "type": null, "letter": null, "defs": []}, {"x": 11, "y": 13, "type": null, "letter": null, "defs": []}, {"x": 12, "y": 13, "type": "LETTER", "letter": "H", "defs": []}, {"x": 0, "y": 14, "type": "DEF", "letter": null, "defs": [{"direction": "RIGHT", "clue_text": ""}, {"direction": "RIGHT_DOWN", "clue_text": ""}]}, {"x": 1, "y": 14, "type": "LETTER", "letter": "S", "defs": []}, {"x": 2, "y": 14, "type": "LETTER", "letter": "O", "defs": []}, {"x": 3, "y": 14, "type": "LETTER", "letter": "P", "defs": []}, {"x": 4, "y": 14, "type": "LETTER", "letter": "O", "defs": []}, {"x": 5, "y": 14, "type": "LETTER", "letter": "R", "defs": []}, {"x": 6, "y": 14, "type": "LETTER", "letter": "I", "defs": []}, {"x": 7, "y": 14, "type": "LETTER", "letter": "F", "defs": []}, {"x": 8, "y": 14, "type": "LETTER", "letter": "I", "defs": []}, {"x": 9, "y": 14, "type": "LETTER", "letter": "Q", "defs": []}, {"x": 10, "y": 14, "type": "LETTER", "letter": "U", "defs": []}, {"x": 11, "y": 14, "type": "LETTER", "letter": "E", "defs": []}, {"x": 12, "y": 14, "type": "DEF", "letter": null, "defs": [{"direction": "DOWN", "clue_text": ""}]}, {"x": 0, "y": 15, "type": null, "letter": null, "defs": []}, {"x": 1, "y": 15, "type": null, "letter": null, "defs": []}, {"x": 2, "y": 15, "type": "LETTER", "letter": "S", "defs": []}, {"x": 3, "y": 15, "type": null, "letter": null, "defs": []}, {"x": 4, "y": 15, "type": null, "letter": null, "defs": []}, {"x": 5, "y": 15, "type": null, "letter": null, "defs": []}, {"x": 6, "y": 15, "type": "DEF", "letter": null, "defs": [{"direction": "DOWN", "clue_text": ""}, {"direction": "RIGHT_DOWN", "clue_text": ""}]}, {"x": 7, "y": 15, "type": "LETTER", "letter": "E", "defs": []}, {"x": 8, "y": 15, "type": "DEF", "letter": null, "defs": [{"direction": "RIGHT", "clue_text": ""}, {"direction": "DOWN", "clue_text": ""}]}, {"x": 9, "y": 15, "type": null, "letter": null, "defs": []}, {"x": 10, "y": 15, "type": null, "letter": null, "defs": []}, {"x": 11, "y": 15, "type": null, "letter": null, "defs": []}, {"x": 12, "y": 15, "type": "LETTER", "letter": "H", "defs": []}, {"x": 0, "y": 16, "type": "DEF", "letter": null, "defs": [{"direction": "RIGHT", "clue_text": ""}, {"direction": "RIGHT_DOWN", "clue_text": ""}]}, {"x": 1, "y": 16, "type": "LETTER", "letter": "D", "defs": []}, {"x": 2, "y": 16, "type": "LETTER", "letter": "E", "defs": []}, {"x": 3, "y": 16, "type": "LETTER", "letter": "L", "defs": []}, {"x": 4, "y": 16, "type": "LETTER", "letter": "A", "defs": []}, {"x": 5, "y": 16, "type": "LETTER", "letter": "T", "defs": []}, {"x": 6, "y": 16, "type": "LETTER", "letter": "E", "defs": []}, {"x": 7, "y": 16, "type": "LETTER", "letter": "U", "defs": []}, {"x": 8, "y": 16, "type": "LETTER", "letter": "R", "defs": []}, {"x": 9, "y": 16, "type": "DEF", "letter": null, "defs": [{"direction": "RIGHT", "clue_text": ""}, {"direction": "RIGHT_DOWN", "clue_text": ""}]}, {"x": 10, "y": 16, "type": "LETTER", "letter": "U", "defs": []}, {"x": 11, "y": 16, "type": "LETTER", "letter": "N", "defs": []}, {"x": 12, "y": 16, "type": "LETTER", "letter": "E", "defs": []}, {"x": 0, "y": 17, "type": null, "letter": null, "defs": []}, {"x": 1, "y": 17, "type": null, "letter": null, "defs": []}, {"x": 2, "y": 17, "type": "DEF", "letter": null, "defs": [{"direction": "RIGHT", "clue_text": ""}, {"direction": "DOWN", "clue_text": ""}, {"direction": "RIGHT_DOWN", "clue_text": ""}]}, {"x": 3, "y": 17, "type": null, "letter": null, "defs": []}, {"x": 4, "y": 17, "type": null, "letter": null, "defs": []}, {"x": 5, "y": 17, "type": null, "letter": null, "defs": []}, {"x": 6, "y": 17, "type": null, "letter": null, "defs": []}, {"x": 7, "y": 17, "type": "DEF", "letter": null, "defs": [{"direction": "RIGHT", "clue_text": ""}, {"direction": "DOWN", "clue_text": ""}, {"direction": "RIGHT_DOWN", "clue_text": ""}]}, {"x": 8, "y": 17, "type": "LETTER", "letter": "U", "defs": []}, {"x": 9, "y": 17, "type": "LETTER", "letter": "S", "defs": []}, {"x": 10, "y": 17, "type": "DEF", "letter": null, "defs": [{"direction": "RIGHT", "clue_text": ""}, {"direction": "DOWN", "clue_text": ""}, {"direction": "RIGHT_DOWN", "clue_text": ""}]}, {"x": 11, "y": 17, "type": null, "letter": null, "defs": []}, {"x": 12, "y": 17, "type": "LETTER", "letter": "C", "defs": []}, {"x": 0, "y": 18, "type": "DEF", "letter": null, "defs": [{"direction": "RIGHT", "clue_text": ""}, {"direction": "RIGHT_DOWN", "clue_text": ""}]}, {"x": 1, "y": 18, "type": "LETTER", "letter": "Z", "defs": []}, {"x": 2, "y": 18, "type": "LETTER", "letter": "I", "defs": []}, {"x": 3, "y": 18, "type": "LETTER", "letter": "M", "defs": []}, {"x": 4, "y": 18, "type": "LETTER", "letter": "B", "defs": []}, {"x": 5, "y": 18, "type": "LETTER", "letter": "A", "defs": []}, {"x": 6, "y": 18, "type": "LETTER", "letter": "B", "defs": []}, {"x": 7, "y": 18, "type": "LETTER", "letter": "W", "defs": []}, {"x": 8, "y": 18, "type": "LETTER", "letter": "E", "defs": []}, {"x": 9, "y": 18, "type": "DEF", "letter": null, "defs": [{"direction": "RIGHT", "clue_text": ""}, {"direction": "DOWN", "clue_text": ""}, {"direction": "RIGHT_DOWN", "clue_text": ""}]}, {"x": 10, "y": 18, "type": "LETTER", "letter": "D", "defs": []}, {"x": 11, "y": 18, "type": "LETTER", "letter": "U", "defs": []}, {"x": 12, "y": 18, "type": "LETTER", "letter": "T", "defs": []}, {"x": 0, "y": 19, "type": null, "letter": null, "defs": []}, {"x": 1, "y": 19, "type": null, "letter": null, "defs": []}, {"x": 2, "y": 19, "type": "LETTER", "letter": "R", "defs": []}, {"x": 3, "y": 19, "type": null, "letter": null, "defs": []}, {"x": 4, "y": 19, "type": null, "letter": null, "defs": []}, {"x": 5, "y": 19, "type": null, "letter": null, "defs": []}, {"x": 6, "y": 19, "type": null, "letter": null, "defs": []}, {"x": 7, "y": 19, "type": null, "letter": null, "defs": []}, {"x": 8, "y": 19, "type": "DEF", "letter": null, "defs": [{"direction": "RIGHT", "clue_text": ""}, {"direction": "RIGHT_DOWN", "clue_text": ""}]}, {"x": 9, "y": 19, "type": null, "letter": null, "defs": []}, {"x": 10, "y": 19, "type": null, "letter": null, "defs": []}, {"x": 11, "y": 19, "type": null, "letter": null, "defs": []}, {"x": 12, "y": 19, "type": "LETTER", "letter": "O", "defs": []}, {"x": 0, "y": 20, "type": "DEF", "letter": null, "defs": [{"direction": "RIGHT", "clue_text": ""}, {"direction": "RIGHT_DOWN", "clue_text": ""}]}, {"x": 1, "y": 20, "type": "LETTER", "letter": "M", "defs": []}, {"x": 2, "y": 20, "type": "LETTER", "letter": "A", "defs": []}, {"x": 3, "y": 20, "type": "LETTER", "letter": "R", "defs": []}, {"x": 4, "y": 20, "type": "LETTER", "letter": "E", "defs": []}, {"x": 5, "y": 20, "type": "LETTER", "letter": "E", "defs": []}, {"x": 6, "y": 20, "type": "DEF", "letter": null, "defs": [{"direction": "RIGHT", "clue_text": ""}]}, {"x": 7, "y": 20, "type": "LETTER", "letter": "L", "defs": []}, {"x": 8, "y": 20, "type": "LETTER", "letter": "A", "defs": []}, {"x": 9, "y": 20, "type": "LETTER", "letter": "B", "defs": []}, {"x": 10, "y": 20, "type": "LETTER", "letter": "E", "defs": []}, {"x": 11, "y": 20, "type": "LETTER", "letter": "U", "defs": []}, {"x": 12, "y": 20, "type": "LETTER", "letter": "R", "defs": []}]}, "logs": ["RUN start seed=1949837216 max_mandatory=5 max_steps=500", "[001] oblig SOPORIFIQUE RIGHT @ (1,14) len=12 pattern=............ +DEF (12,14)", "[002] oblig LUGUBRE RIGHT @ (1,12) len=12 pattern=............ +DEF (8,12)", "[003] oblig OURLE DOWN @ (8,1) len=11 pattern=........... +DEF (8,6)", "[004] oblig IRE RIGHT @ (9,6) len=4 pattern=.... +DEF (12,6)", "[005] oblig VERSATILE RIGHT @ (1,8) len=12 pattern=............ +DEF (10,8)", "[006] fill TA RIGHT @ (11,8) len=2 pattern=..", "[007] fill LIMA RIGHT @ (9,12) len=4 pattern=....", "[008] fill HECTOR DOWN @ (12,15) len=6 pattern=......", "[009] fill LATTE DOWN @ (12,1) len=5 pattern=.....", "[010] fill CONFORT DOWN @ (10,1) len=7 pattern=.....R.", "[011] fill TRIMER RIGHT @ (1,4) len=12 pattern=.......L.F.T +DEF (7,4)", "[012] fill POCHES RIGHT @ (1,6) len=7 pattern=....... +DEF (7,6)", "[013] fill ZIMBABWE RIGHT @ (1,18) len=12 pattern=...........T +DEF (9,18)", "[014] fill DUT RIGHT @ (10,18) len=3 pattern=..T", "[015] fill MAREE RIGHT @ (1,20) len=12 pattern=...........R +DEF (6,20)", "[016] fill DELATEUR RIGHT @ (1,16) len=12 pattern=...........E +DEF (9,16)", "[017] fill LUMINEUX RIGHT @ (1,10) len=12 pattern=............ +DEF (9,10)", "[018] fill DUE RIGHT @ (10,10) len=3 pattern=...", "[019] fill UNE RIGHT @ (10,16) len=3 pattern=..E", "[020] fill EXCLUT RIGHT @ (1,2) len=12 pattern=.......U.O.A +DEF (7,2)", "[021] fill STORES DOWN @ (6,1) len=19 pattern=.T.R.S.T.E.R.I.E.B. +DEF (6,7)", "[022] fill SITUEE DOWN @ (7,7) len=14 pattern=.I.U.E.F.U.W.. +DEF (7,13)", "[023] fill LABEUR RIGHT @ (7,20) len=6 pattern=.....R", "[024] fill LAVE DOWN @ (12,7) len=7 pattern=.A.E.A. +DEF (12,11)", "[025] fill AH DOWN @ (12,12) len=2 pattern=A.", "[026] fill SA RIGHT @ (7,7) len=6 pattern=S..T.L +DEF (9,7)", "[027] fill FOU DOWN @ (5,0) len=21 pattern=..U.E.E.A.N.B.R.T.A.E +DEF (5,3)", "[028] fill OUEST DOWN @ (1,0) len=21 pattern=..E.T.P.V.L.L.S.D.Z.M +DEF (1,5)", "[029] fill AL DOWN @ (7,0) len=2 pattern=..", "[030] fill TEE DOWN @ (6,8) len=12 pattern=T.E.R.I.E.B. +DEF (6,11)", "[031] fill EU DOWN @ (9,8) len=2 pattern=E.", "[032] fill FEU DOWN @ (7,14) len=7 pattern=F.U.W.L +DEF (7,17)", "[033] fill ERE DOWN @ (5,4) len=17 pattern=E.E.A.N.B.R.T.A.E +DEF (5,7)", "[034] fill IL DOWN @ (9,11) len=5 pattern=.L.Q. +DEF (9,13)", "[035] fill ABC DOWN @ (3,0) len=21 pattern=..C.I.C.R.M.G.P.L.M.R +DEF (3,3)", "[036] fill OS RIGHT @ (0,3) len=3 pattern=.S. +DEF (2,3)", "[037] fill RIO DOWN @ (2,4) len=17 pattern=R.O.E.U.U.O.E.I.A +DEF (2,7)", "[038] fill TU RIGHT @ (0,1) len=13 pattern=.U.B.OSLO.C.L +DEF (2,1)", "[039] fill CI DOWN @ (8,13) len=8 pattern=.I.R.E.A +DEF (8,15)", "[040] fill SAM RIGHT @ (0,9) len=13 pattern=......ET.U..V +DEF (3,9)", "[041] fill RAI DOWN @ (6,12) len=8 pattern=R.I.E.B. +DEF (6,15)", "[042] fill RUE DOWN @ (8,16) len=5 pattern=R.E.A +DEF (8,19)", "[043] fill EMU DOWN @ (2,8) len=13 pattern=EMU.U.O.E.I.A +DEF (2,11)", "[044] fill NE RIGHT @ (0,13) len=7 pattern=......A +DEF (2,13)", "[045] fill OSE DOWN @ (2,14) len=7 pattern=O.E.I.A +DEF (2,17)", "[046] fill US RIGHT @ (8,17) len=5 pattern=U...C +DEF (10,17)", "[047] fill IRA DOWN @ (2,18) len=3 pattern=I.A", "STOP: aucun mot placable.", "DONE: placed=47 unplaced=0", "[001] oblig SOPORIFIQUE RIGHT @ (1,14) len=11 pattern=SOPORIFIQUE", "HB steps=1 queue_idx=1 used_slots=1", "[002] oblig LUGUBRE RIGHT @ (1,12) len=7 pattern=LUGUBRE", "[003] oblig OURLE DOWN @ (8,1) len=5 pattern=OURLE", "[004] oblig IRE RIGHT @ (9,6) len=3 pattern=IRE", "[005] oblig VERSATILE RIGHT @ (1,8) len=9 pattern=VERSATILE", "STOP: aucun mot placable.", "DONE: placed=5 unplaced=0"]}